dtcm2.py
dtcm2-2.0.2.dist-info/LICENSE
dtcm2-2.0.2.dist-info/METADATA
dtcm2-2.0.2.dist-info/WHEEL
dtcm2-2.0.2.dist-info/top_level.txt
dtcm2-2.0.2.dist-info/RECORD
