Metadata-Version: 2.1
Name: dtcm2
Version: 2.0.2
Summary: Declassed Tor Circuits Manager version 2
Home-page: https://declassed.art/repository/dtcm2
Author: AXY
Author-email: axy@declassed.art
License: UNKNOWN
Platform: UNKNOWN
Classifier: Programming Language :: Python :: 3
Classifier: License :: OSI Approved :: GNU Lesser General Public License v3 (LGPLv3)
Classifier: Operating System :: OS Independent
Classifier: Intended Audience :: Developers
Classifier: Development Status :: 4 - Beta
Classifier: Topic :: Internet :: WWW/HTTP
Requires-Python: >=3.7
License-File: LICENSE
Requires-Dist: torcontrol
